logger_utils/__init__.py
logger_utils/constants.py
logger_utils/custom_formatter.py
logger_utils/level_mapper.py
logger_utils/logger_factory.py
logger_utils/logger_injector.py
color_logger_utils-0.1.0.dist-info/METADATA
color_logger_utils-0.1.0.dist-info/WHEEL
color_logger_utils-0.1.0.dist-info/top_level.txt
color_logger_utils-0.1.0.dist-info/RECORD
